chessboard/__init__.py
chessboard/logger.py
chessboard/version.py
chessboardCLI-1.3.8.dist-info/LICENSE.txt
chessboardCLI-1.3.8.dist-info/METADATA
chessboardCLI-1.3.8.dist-info/WHEEL
chessboardCLI-1.3.8.dist-info/top_level.txt
chessboardCLI-1.3.8.dist-info/RECORD
