Metadata-Version: 2.1
Name: chessboardCLI
Version: 1.3.8
Summary: Chessboard generator in command line
Home-page: https://github.com/houluy/chessboard
Author: Houlu
Author-email: houlu8674@bupt.edu.cn
License: MIT
Keywords: chessboard
Platform: UNKNOWN
Classifier: Development Status :: 5 - Production/Stable
Classifier: Intended Audience :: Developers
Classifier: Topic :: Software Development :: Libraries :: Python Modules
Classifier: Programming Language :: Python :: 3
Classifier: Programming Language :: Python :: 3.3
Classifier: Programming Language :: Python :: 3.4
Classifier: Programming Language :: Python :: 3.5
Classifier: Programming Language :: Python :: 3.6
Requires-Python: >=3
Requires-Dist: colorline (>=1.0.3)
